cloner/__init__.py
cloner/google_connections.py
googledrive_cloner/__init__.py
googledrive_cloner/google_connections.py
googledrive_cloner-1.0.3.dist-info/LICENSE
googledrive_cloner-1.0.3.dist-info/METADATA
googledrive_cloner-1.0.3.dist-info/WHEEL
googledrive_cloner-1.0.3.dist-info/top_level.txt
googledrive_cloner-1.0.3.dist-info/RECORD
