Metadata-Version: 2.1
Name: googledrive-cloner
Version: 1.0.3
Summary: Clone folders in Google Drive
Home-page: https://github.com/NickHilton/googledrivecloner
Author: Nick Hilton
Author-email: nicholas.w.hilton@gmail.com
License: MIT
Platform: UNKNOWN
Classifier: License :: OSI Approved :: MIT License
Classifier: Programming Language :: Python :: 3
License-File: LICENSE
Requires-Dist: google-auth-oauthlib (<0.5,>=0.4.3)
Requires-Dist: google-api-python-client (<2.1,>=2.0.2)
